[
  { "tries": 2, "zone": "12:00 a.m.", "color": "yellow" },
  { "tries": 2, "zone": "12:30 a.m.", "color": "yellow" },
  { "tries": 2, "zone": "1:00 a.m.", "color": "yellow" },
  { "tries": 0, "zone": "1:30 a.m.", "color": "green" },
  { "tries": 1, "zone": "2:00 a.m.", "color": "green" },
  { "tries": 2, "zone": "2:30 a.m.", "color": "yellow" },
  { "tries": 2, "zone": "3:00 a.m.", "color": "yellow" },
  { "tries": 0, "zone": "3:30 a.m.", "color": "green" },
  { "tries": 0, "zone": "4:00 a.m.", "color": "green" },
  { "tries": 2, "zone": "4:30 a.m.", "color": "yellow" },
  { "tries": 1, "zone": "5:00 a.m.", "color": "yellow" },
  { "tries": 3, "zone": "5:30 a.m.", "color": "yellow" },
  { "tries": 2, "zone": "6:00 a.m.", "color": "yellow" },
  { "tries": 1, "zone": "6:30 a.m.", "color": "green" },
  { "tries": 1, "zone": "7:00 a.m.", "color": "green" },
  { "tries": 2, "zone": "7:30 a.m.", "color": "yellow" },
  { "tries": 2, "zone": "8:00 a.m.", "color": "yellow" },
  { "tries": 4, "zone": "8:30 a.m.", "color": "yellow" },
  { "tries": 1, "zone": "9:00 a.m.", "color": "green" },
  { "tries": 0, "zone": "9:30 a.m.", "color": "green" },
  { "tries": 7, "zone": "10:00 a.m.", "color": "red" },
  { "tries": 2, "zone": "10:30 a.m.", "color": "yellow" },
  { "tries": 1, "zone": "11:00 a.m.", "color": "yellow" },
  { "tries": 1, "zone": "11:30 a.m.", "color": "yellow" },
  { "tries": 1, "zone": "12:00 p.m.", "color": "yellow" },
  { "tries": 1, "zone": "12:30 p.m.", "color": "yellow" },
  { "tries": 0, "zone": "1:00 p.m.", "color": "green" },
  { "tries": 2, "zone": "1:30 p.m.", "color": "yellow" },
  { "tries": 1, "zone": "2:00 p.m.", "color": "yellow" },
  { "tries": 2, "zone": "2:30 p.m.", "color": "yellow" },
  { "tries": 0, "zone": "3:00 p.m.", "color": "green" },
  { "tries": 1, "zone": "3:30 p.m.", "color": "green" },
  { "tries": 2, "zone": "4:00 p.m.", "color": "yellow" },
  { "tries": 1, "zone": "4:30 p.m.", "color": "yellow" },
  { "tries": 3, "zone": "5:00 p.m.", "color": "yellow" },
  { "tries": 2, "zone": "5:30 p.m.", "color": "yellow" },
  { "tries": 2, "zone": "6:00 p.m.", "color": "yellow" },
  { "tries": 1, "zone": "6:30 p.m.", "color": "green" },
  { "tries": 0, "zone": "7:00 p.m.", "color": "green" },
  { "tries": 2, "zone": "7:30 p.m.", "color": "yellow" },
  { "tries": 1, "zone": "8:00 p.m.", "color": "yellow" },
  { "tries": 2, "zone": "8:30 p.m.", "color": "yellow" },
  { "tries": 4, "zone": "9:00 p.m.", "color": "red" },
  { "tries": 2, "zone": "9:30 p.m.", "color": "yellow" },
  { "tries": 1, "zone": "10:00 p.m.", "color": "yellow" },
  { "tries": 0, "zone": "10:30 p.m.", "color": "green" },
  { "tries": 0, "zone": "11:00 p.m.", "color": "green" },
  { "tries": 0, "zone": "11:30 p.m.", "color": "green" },
  { "tries": 72, "zone": "Total", "color": "" }
]
